{
  "GeneratePacklistDocument": "Generate Packlist Document",
  "GenerateDeliveryNote": "Generate Delivery Note",
  "EmptyPackage": "No Package Has Been Created Yet!",
  "Summery": "Summary",
  "DonePacking": "Done Packing",
  "PackerDashboard": "Packer Dashboard",
  "OrderID": "Order ID",
  "PackageID": "Package ID",
  "ProductBarcode": "Product Barcode",
  "Order": "Order",
  "Box": "Box",
  "Product": "Product",
  "OrderPositions": "Order Positions",
  "DoNotOrderSelected": "No Order Has Been Selected!",
  "NoData": "No Data",
  "NoName": "No Name",
  "ProductsInformation": "Products Information",
  "DoNotProductSelected": "No Product Has Been Selected!",
  "CloseBox": "Close Box",
  "CloseBoxShipping": "Close Box With Shipping",
  "CloseBoxAndGenerateDelivery": "Close Box and Generate Delivery with Shipping",
  "TotalWeight": "Total Weight",
  "BoxInformation": "Box Information",
  "GenerateDelivery": "Close Box and Generate Delivery",
  "RequiredSerialNumber": "Serial Number is required",
  "DuplicateSerialNumber": "Serial Number is duplicated",
  "Number": "Number",
  "ProductVariationSerialNumber": "Product Variation Serial Number",
  "EnterSerialNumber": "Enter Serial Number",
  "SelectSerialNumber": "Select a serial number you want to remove",
  "OrderSelected": "Order Selected!",
  "BoxSelected": "Box Selected!",
  "ProductSelected": "Product Selected!",
  "ChoseOrder": "You had chose your order before! please continue...",
  "ChoseBox": "You had chose your box before! please continue...",
  "ChoseOrderFirst": "You should choose your order first! please get back...",
  "ChoseBoxFirst": "You should choose your box first! please get back...",
  "OrderIsNotInPackingStatus": "Order Is Not In Packing Status!",
  "CreateShippingLabel": "Create Shipping Label",
  "RemovePacking": "Remove Packing",
  "WaitResponse": "Please wait for response",
  "OnlyProductBarcode":"Only product barcode is acceptable"
}
